single_agent/server.py
contextual_mcp_server-0.1.0.dist-info/METADATA
contextual_mcp_server-0.1.0.dist-info/WHEEL
contextual_mcp_server-0.1.0.dist-info/top_level.txt
contextual_mcp_server-0.1.0.dist-info/RECORD
