Metadata-Version: 2.4
Name: contextual-mcp-server
Version: 0.1.0
Summary: Add your description here
Requires-Python: >=3.10
Requires-Dist: contextual-client>=0.5.1
Requires-Dist: httpx>=0.28.1
Requires-Dist: mcp[cli]>=1.6.0
Requires-Dist: dotenv
Requires-Dist: uv
Requires-Dist: tiktoken
